klausen/__init__.py
klausen/named_parameters.py
klausen-0.1.1.dist-info/LICENSE
klausen-0.1.1.dist-info/METADATA
klausen-0.1.1.dist-info/WHEEL
klausen-0.1.1.dist-info/top_level.txt
klausen-0.1.1.dist-info/RECORD
