Metadata-Version: 2.1
Name: klausen
Version: 0.1.1
Summary: Parameterized model framework in Python
Home-page: https://github.com/cmutel/klausen
Author: Chris Mutel
Author-email: cmutel@gmail.com
License: BSD 3-Clause License
Requires-Dist: numpy
Requires-Dist: scipy
Requires-Dist: stats-arrays
